CHANGES.txt
DEPENDENCES.txt
README.txt
setup.py
src/ng/__init__.py
src/ng.app.rubricator.algorithm.tag.egg-info/PKG-INFO
src/ng.app.rubricator.algorithm.tag.egg-info/SOURCES.txt
src/ng.app.rubricator.algorithm.tag.egg-info/dependency_links.txt
src/ng.app.rubricator.algorithm.tag.egg-info/namespace_packages.txt
src/ng.app.rubricator.algorithm.tag.egg-info/not-zip-safe
src/ng.app.rubricator.algorithm.tag.egg-info/requires.txt
src/ng.app.rubricator.algorithm.tag.egg-info/top_level.txt
src/ng/app/__init__.py
src/ng/app/rubricator/__init__.py
src/ng/app/rubricator/algorithm/__init__.py
src/ng/app/rubricator/algorithm/tag/__init__.py
src/ng/app/rubricator/algorithm/tag/configure.zcml
src/ng/app/rubricator/algorithm/tag/interfaces.py
src/ng/app/rubricator/algorithm/tag/ng.app.rubricator.algorithm.tag.txt
src/ng/app/rubricator/algorithm/tag/rubricalgorithmtag.py
src/ng/app/rubricator/algorithm/tag/browser/__init__.py
src/ng/app/rubricator/algorithm/tag/browser/configure.zcml
src/ng/app/rubricator/algorithm/tag/browser/reindex.pt
src/ng/app/rubricator/algorithm/tag/etc/ng.app.rubricator.algorithm.tag-configure.zcml
